amirpdf/__init__.py
amirpdf/pdf2image.py
amirpdf/pdf2txt.py
Amirpdfconverter-1.0.dist-info/LICENSE
Amirpdfconverter-1.0.dist-info/METADATA
Amirpdfconverter-1.0.dist-info/WHEEL
Amirpdfconverter-1.0.dist-info/top_level.txt
Amirpdfconverter-1.0.dist-info/RECORD
